witch_msa/__init__.py
witch_msa/configs.py
witch_msa/default.config
witch_msa/init_configs.py
witch_msa/gcmm/__init__.py
witch_msa/gcmm/algorithm.py
witch_msa/gcmm/aligner.py
witch_msa/gcmm/backbone.py
witch_msa/gcmm/callback.py
witch_msa/gcmm/decompose_tree.py
witch_msa/gcmm/gcmm.py
witch_msa/gcmm/loader.py
witch_msa/gcmm/merger.py
witch_msa/gcmm/results_handler.py
witch_msa/gcmm/task.py
witch_msa/gcmm/tree.py
witch_msa/gcmm/weighting.py
witch_msa/helpers/__init__.py
witch_msa/helpers/alignment_tools.py
witch_msa/helpers/general_tools.py
witch_msa/helpers/math_utils.py
witch_msa/helpers/pyhmmer_tools.py
witch_msa/tools/macOS/FastTreeMP
witch_msa/tools/macOS/hmmalign
witch_msa/tools/macOS/hmmbuild
witch_msa/tools/macOS/hmmsearch
witch_msa/tools/macOS/mafft
witch_msa/tools/macOS/mcl
witch_msa/tools/magus/README.md
witch_msa/tools/magus/configuration.py
witch_msa/tools/magus/magus.py
witch_msa/tools/magus/align/__init__.py
witch_msa/tools/magus/align/aligner.py
witch_msa/tools/magus/align/alignment_context.py
witch_msa/tools/magus/align/decompose/__init__.py
witch_msa/tools/magus/align/decompose/decomposer.py
witch_msa/tools/magus/align/decompose/initial_tree.py
witch_msa/tools/magus/align/decompose/kmh.py
witch_msa/tools/magus/align/merge/__init__.py
witch_msa/tools/magus/align/merge/alignment_graph.py
witch_msa/tools/magus/align/merge/alignment_writer.py
witch_msa/tools/magus/align/merge/merger.py
witch_msa/tools/magus/align/merge/optimizer.py
witch_msa/tools/magus/align/merge/graph_build/__init__.py
witch_msa/tools/magus/align/merge/graph_build/graph_builder.py
witch_msa/tools/magus/align/merge/graph_cluster/__init__.py
witch_msa/tools/magus/align/merge/graph_cluster/clean_clusters.py
witch_msa/tools/magus/align/merge/graph_cluster/clusterer.py
witch_msa/tools/magus/align/merge/graph_cluster/mcl.py
witch_msa/tools/magus/align/merge/graph_cluster/mlr_mcl.py
witch_msa/tools/magus/align/merge/graph_cluster/rg.py
witch_msa-1.0.10.dist-info/licenses/LICENSE
witch_msa-1.0.10.dist-info/METADATA
witch_msa-1.0.10.dist-info/WHEEL
witch_msa-1.0.10.dist-info/top_level.txt
witch_msa-1.0.10.dist-info/RECORD
