Metadata-Version: 2.4
Name: witch-msa
Version: 1.0.10
Summary: WITCH - A Multiple Sequence Alignment Tool
Author-email: Chengze Shen <chengze5@illinois.edu>
License:                     GNU GENERAL PUBLIC LICENSE
Project-URL: Homepage, https://github.com/c5shen/WITCH
Project-URL: Changelog, https://github.com/c5shen/WITCH/blob/main/CHANGELOG.rst
Classifier: Development Status :: 4 - Beta
Classifier: Operating System :: OS Independent
Classifier: Intended Audience :: Developers
Classifier: Intended Audience :: Science/Research
Classifier: Topic :: Scientific/Engineering :: Bio-Informatics
Classifier: Topic :: Software Development
Classifier: License :: OSI Approved :: GNU General Public License (GPL)
Classifier: Programming Language :: Python
Classifier: Programming Language :: Python :: 3
Classifier: Programming Language :: Python :: 3.7
Classifier: Programming Language :: Python :: 3.8
Classifier: Programming Language :: Python :: 3.9
Classifier: Programming Language :: Python :: 3.10
Classifier: Programming Language :: Python :: 3.11
Classifier: Programming Language :: Python :: 3.12
Requires-Python: >=3.7
License-File: LICENSE
Requires-Dist: cython>=0.29
Requires-Dist: configparser>=5.0.0
Requires-Dist: DendroPy>=4.4.0
Requires-Dist: numpy>=1.15
Requires-Dist: psutil>=5.0
Requires-Dist: tqdm>=4.0.0
Dynamic: license-file
